CHANGES.rst
LICENSE.txt
MANIFEST.in
README.rst
setup.py
src/bst/__init__.py
src/bst.pygasus.resources.egg-info/PKG-INFO
src/bst.pygasus.resources.egg-info/SOURCES.txt
src/bst.pygasus.resources.egg-info/dependency_links.txt
src/bst.pygasus.resources.egg-info/entry_points.txt
src/bst.pygasus.resources.egg-info/namespace_packages.txt
src/bst.pygasus.resources.egg-info/not-zip-safe
src/bst.pygasus.resources.egg-info/requires.txt
src/bst.pygasus.resources.egg-info/top_level.txt
src/bst/pygasus/__init__.py
src/bst/pygasus/resources/__init__.py
src/bst/pygasus/resources/boostrap.py
src/bst/pygasus/resources/configure.zcml
src/bst/pygasus/resources/fanstatic.py
src/bst/pygasus/resources/html.py
src/bst/pygasus/resources/interfaces.py
src/bst/pygasus/resources/templates/index.html